realsense_depth_detector/__init__.py
realsense_depth_detector/config.py
realsense_depth_detector/detector.py
realsense_depth_detector-0.1.0.dist-info/LICENSE
realsense_depth_detector-0.1.0.dist-info/METADATA
realsense_depth_detector-0.1.0.dist-info/WHEEL
realsense_depth_detector-0.1.0.dist-info/top_level.txt
realsense_depth_detector-0.1.0.dist-info/RECORD
