Metadata-Version: 2.1
Name: realsense-depth-detector
Version: 0.1.0
Summary: A package for object detection with depth using RealSense cameras
Home-page: https://github.com/ekts00243/realsense_depth.git
Author: Harikrishna U Kamath
Author-email: ekts00243@gmail.com
License: UNKNOWN
Keywords: realsense,depth detection,computer vision,yolo,object detection
Platform: UNKNOWN
Classifier: Development Status :: 3 - Alpha
Classifier: Intended Audience :: Developers
Classifier: License :: OSI Approved :: MIT License
Classifier: Operating System :: OS Independent
Classifier: Programming Language :: Python :: 3
Classifier: Programming Language :: Python :: 3.8
Classifier: Programming Language :: Python :: 3.9
Classifier: Programming Language :: Python :: 3.10
Requires-Python: >=3.8
License-File: LICENSE
Requires-Dist: numpy
Requires-Dist: opencv-python
Requires-Dist: pyrealsense2
Requires-Dist: ultralytics
